Metadata-Version: 2.1
Name: MotionMySql
Version: 0.0.1
Summary: Dynamically constructing add/delete/reference statements using python
Home-page: https://github.com/CasearF/MotionMySql
Author: CasearF
Author-email: CasearF <asearx@gmail.com>
Project-URL: Homepage, https://github.com/CasearF/MotionMySql
Project-URL: Issues, https://github.com/CasearF/MotionMySql/issues
Classifier: Programming Language :: Python :: 3
Classifier: License :: OSI Approved :: MIT License
Classifier: Operating System :: OS Independent
Requires-Python: >=3.6
License-File: LICENSE
